app/__init__.py
app/approval_bridge.py
app/cli.py
app/conversation_manager.py
app/fix_tools_json.py
app/server.py
app/state.py
app/tool_registry.py
app/handlers/__init__.py
app/handlers/approval.py
app/handlers/base.py
app/handlers/chat.py
app/handlers/conversation.py
app/handlers/edit.py
app/handlers/history.py
app/handlers/models.py
app/handlers/registry.py
app/handlers/settings.py
app/handlers/voice.py
app/services/__init__.py
app/services/conversation_service.py
app/services/model_service.py
app/services/workspace_service.py
app/voice/__init__.py
app/voice/audio_utils.py
app/voice/config.py
app/voice/transcription_service.py
app/voice/providers/__init__.py
app/voice/providers/base.py
app/voice/providers/local_whisper.py
app/voice/providers/openai_whisper.py
app/workspace/calculator.py
app/workspace/example.py
app/workspace/example_error.py
app/workspace/hello_world.py
app/workspace/math_operations.py
app/workspace/quick_math.py
app/workspace/random_fun.py
app/workspace/shopping_cart.py
app/workspace/suspicious_info_gather.py
app/workspace/test_shopping_cart.py
orchestral/__init__.py
orchestral/agent/__init__.py
orchestral/agent/agent.py
orchestral/context/__init__.py
orchestral/context/context.py
orchestral/context/message.py
orchestral/context/summarization/prompts.py
orchestral/context/summarization/summarizer.py
orchestral/llm/__init__.py
orchestral/llm/routers.py
orchestral/llm/anthropic/client.py
orchestral/llm/anthropic/model_details.py
orchestral/llm/anthropic/parsers.py
orchestral/llm/anthropic/pricing_model.py
orchestral/llm/anthropic/tool_adapter.py
orchestral/llm/base/llm.py
orchestral/llm/base/response.py
orchestral/llm/base/tool_call.py
orchestral/llm/base/usage.py
orchestral/llm/bedrock/__init__.py
orchestral/llm/bedrock/client.py
orchestral/llm/bedrock/model_details.py
orchestral/llm/bedrock/parsers.py
orchestral/llm/bedrock/pricing_model.py
orchestral/llm/bedrock/tool_adapter.py
orchestral/llm/google/client.py
orchestral_sdk-0.2.1.dist-info/METADATA
orchestral_sdk-0.2.1.dist-info/WHEEL
orchestral_sdk-0.2.1.dist-info/entry_points.txt
orchestral_sdk-0.2.1.dist-info/top_level.txt
orchestral_sdk-0.2.1.dist-info/RECORD
