Metadata-Version: 2.4
Name: orchestral-sdk
Version: 0.2.1
Summary: Production-ready AI framework for building LLM-powered applications with unified tool calling across multiple providers
Author-email: Alex Roman <alex@orchestral.ai>
License: Proprietary - All Rights Reserved
Project-URL: Homepage, https://orchestral.ai
Project-URL: Documentation, https://orchestral.ai/docs
Project-URL: Issues, https://orchestral.ai/support
Keywords: ai,llm,agent,anthropic,openai,claude,gpt,chatbot,assistant,framework,tool-calling,multi-provider
Classifier: Development Status :: 4 - Beta
Classifier: Intended Audience :: Developers
Classifier: License :: Other/Proprietary License
Classifier: Programming Language :: Python :: 3
Classifier: Programming Language :: Python :: 3.12
Classifier: Programming Language :: Python :: 3.13
Classifier: Topic :: Scientific/Engineering :: Artificial Intelligence
Classifier: Topic :: Software Development :: Libraries :: Application Frameworks
Requires-Python: >=3.12
Requires-Dist: pydantic>=2.11.7
Requires-Dist: anthropic>=0.64.0
Requires-Dist: openai>=1.102.0
Requires-Dist: google-generativeai>=0.8.3
Requires-Dist: ollama>=0.5.1
Requires-Dist: groq>=0.22.0
Requires-Dist: mistralai>=1.2.0
Requires-Dist: boto3>=1.35.0
Requires-Dist: python-dotenv>=1.1.1
Requires-Dist: numpy>=1.24.0
Requires-Dist: pandas>=2.0.0
Requires-Dist: matplotlib>=3.7.0
Requires-Dist: scipy>=1.10.0
Requires-Dist: requests>=2.28.0
Requires-Dist: pillow>=10.0.0
Requires-Dist: pexpect>=4.8.0; sys_platform != "win32"
Requires-Dist: wexpect>=4.0.0; sys_platform == "win32"
Requires-Dist: setuptools<81; sys_platform == "win32"
Requires-Dist: rich>=13.0.0
Requires-Dist: fastapi>=0.100.0
Requires-Dist: uvicorn>=0.23.0
Requires-Dist: websockets>=11.0.3
Dynamic: requires-python
